ss_utils_docker/__init__.py
ss_utils_docker/cli.py
ss_utils_docker/config.py
ss_utils_docker-0.0.1.dist-info/METADATA
ss_utils_docker-0.0.1.dist-info/WHEEL
ss_utils_docker-0.0.1.dist-info/entry_points.txt
ss_utils_docker-0.0.1.dist-info/RECORD
